{
    "data": [
        {
            "conversation_id": "1620553977367785472",
            "reply_settings": "everyone",
            "geo": {
                "place_id": "c3f37afa9efcf94b"
            },
            "referenced_tweets": [
                {
                    "type": "quoted",
                    "id": "1620547819546480640"
                }
            ],
            "lang": "en",
            "text": "We are going to get fully GPU accelerated AI/ML support in Python + Wasm. On WasmEdge, we already support #TensorFlow and #PyTorch in our Rust API. It is just one step away from creating Python APIs for them. Anyone interested? :)\n\nhttps://t.co/ltoYc1azy8 https://t.co/cyrXFkD9HG",
            "id": "1620553977367785472",
            "edit_history_tweet_ids": [
                "1620553977367785472"
            ],
            "created_at": "2023-01-31T22:45:51.000Z",
            "author_id": "1397415557767471107",
            "public_metrics": {
                "retweet_count": 4,
                "reply_count": 0,
                "like_count": 24,
                "quote_count": 0,
                "impression_count": 1252
            }
        },
        {
            "conversation_id": "1620542552293122048",
            "reply_settings": "everyone",
            "geo": {
                "place_id": "01a9a39529b27f36",
                "coordinates": {
                    "type": "Point",
                    "coordinates": [
                        -74.01658354,
                        40.7153379
                    ]
                }
            },
            "lang": "en",
            "text": "18 more bike docks added at the Vesey Pl &amp; River Terrace Citi Bike station in Battery Park City, Manhattan https://t.co/iNpHJuLlf8 https://t.co/6GQ4T6pq48",
            "id": "1620542552293122048",
            "edit_history_tweet_ids": [
                "1620542552293122048"
            ],
            "created_at": "2023-01-31T22:00:27.000Z",
            "author_id": "1450989570200375299",
            "public_metrics": {
                "retweet_count": 0,
                "reply_count": 0,
                "like_count": 0,
                "quote_count": 0,
                "impression_count": 96
            }
        }
    ],
    "includes": {
        "users": [
            {
                "public_metrics": {
                    "followers_count": 1303,
                    "following_count": 536,
                    "tweet_count": 356,
                    "listed_count": 23
                },
                "username": "realwasmedge",
                "id": "1397415557767471107",
                "description": "The WebAssembly for Edge Computing runtime project hosted by CNCF and Linux Foundation. https://t.co/YTx04KgHfr",
                "created_at": "2021-05-26T04:54:03.000Z",
                "verified": false,
                "name": "wasmedge"
            },
            {
                "public_metrics": {
                    "followers_count": 139,
                    "following_count": 19,
                    "tweet_count": 536,
                    "listed_count": 3
                },
                "username": "MoreCitiBikes",
                "id": "1450989570200375299",
                "description": "For a better NYC, what do we want? More Citi Bikes. (Unofficial) bot posting when and where @CitibikeNYC adds more docks",
                "created_at": "2021-10-21T00:58:49.000Z",
                "verified": false,
                "name": "More Citi Bikes"
            }
        ],
        "places": [
            {
                "place_type": "city",
                "country_code": "US",
                "country": "United States",
                "id": "c3f37afa9efcf94b",
                "name": "Austin",
                "full_name": "Austin, TX",
                "geo": {
                    "type": "Feature",
                    "bbox": [
                        -97.928935,
                        30.127892,
                        -97.5805133,
                        30.5187994
                    ],
                    "properties": {}
                }
            },
            {
                "place_type": "city",
                "country_code": "US",
                "country": "United States",
                "id": "01a9a39529b27f36",
                "name": "Manhattan",
                "full_name": "Manhattan, NY",
                "geo": {
                    "type": "Feature",
                    "bbox": [
                        -74.026675,
                        40.683935,
                        -73.910408,
                        40.877483
                    ],
                    "properties": {}
                }
            }
        ]
    },
    "meta": {
        "newest_id": "1620553977367785472",
        "oldest_id": "1620542552293122048",
        "result_count": 2
    }
}